deepconsensus/__init__.py
deepconsensus/cli.py
deepconsensus/inference/__init__.py
deepconsensus/inference/quick_inference.py
deepconsensus/inference/quick_inference_test.py
deepconsensus/models/__init__.py
deepconsensus/models/attention_layer.py
deepconsensus/models/convert_to_saved_model.py
deepconsensus/models/data_providers.py
deepconsensus/models/data_providers_test.py
deepconsensus/models/encoder_stack.py
deepconsensus/models/ffn_layer.py
deepconsensus/models/losses_and_metrics.py
deepconsensus/models/losses_and_metrics_test.py
deepconsensus/models/model_configs.py
deepconsensus/models/model_distillation.py
deepconsensus/models/model_distillation_test.py
deepconsensus/models/model_inference.py
deepconsensus/models/model_inference_test.py
deepconsensus/models/model_inference_transforms.py
deepconsensus/models/model_inference_transforms_test.py
deepconsensus/models/model_train_custom_loop.py
deepconsensus/models/model_train_custom_loop_test.py
deepconsensus/models/model_utils.py
deepconsensus/models/model_utils_test.py
deepconsensus/models/networks.py
deepconsensus/models/networks_test.py
deepconsensus/models/transformer_basic_params.py
deepconsensus/postprocess/__init__.py
deepconsensus/postprocess/stitch_utils.py
deepconsensus/postprocess/stitch_utils_test.py
deepconsensus/preprocess/__init__.py
deepconsensus/preprocess/pre_lib.py
deepconsensus/preprocess/pre_lib_test.py
deepconsensus/preprocess/preprocess.py
deepconsensus/preprocess/preprocess_test.py
deepconsensus/quality_calibration/__init__.py
deepconsensus/quality_calibration/calculate_baseq_calibration.py
deepconsensus/quality_calibration/calculate_baseq_calibration_test.py
deepconsensus/quality_calibration/calibration_lib.py
deepconsensus/quality_calibration/calibration_lib_test.py
deepconsensus/quality_calibration/filter_reads.py
deepconsensus/quality_calibration/filter_reads_test.py
deepconsensus/utils/__init__.py
deepconsensus/utils/colab_utils.py
deepconsensus/utils/dc_constants.py
deepconsensus-1.2.0.dist-info/LICENSE
deepconsensus-1.2.0.dist-info/METADATA
deepconsensus-1.2.0.dist-info/WHEEL
deepconsensus-1.2.0.dist-info/entry_points.txt
deepconsensus-1.2.0.dist-info/top_level.txt
deepconsensus-1.2.0.dist-info/RECORD
