Metadata-Version: 2.1
Name: deepconsensus
Version: 1.2.0
Summary: DeepConsensus
Home-page: https://github.com/google/deepconsensus
Author: Google LLC
Keywords: bioinformatics
Requires-Python: >=3.6
License-File: LICENSE
Requires-Dist: pandas (==1.5.1)
Requires-Dist: tf-models-official (==2.9.1)
Requires-Dist: pyyaml (==5.4.1)
Requires-Dist: ml-collections (==0.1.1)
Requires-Dist: absl-py (==1.0.0)
Requires-Dist: keras (==2.9.0)
Requires-Dist: pysam (==0.19.0)
Provides-Extra: cpu
Requires-Dist: intel-tensorflow (==2.9.1) ; extra == 'cpu'
Provides-Extra: gpu
Requires-Dist: tensorflow-gpu (==2.9.1) ; extra == 'gpu'
